funfedi_results/__init__.py
funfedi_results/__main__.py
funfedi_results/latest.py
funfedi_results/test_init.py
funfedi_results/allure/__init__.py
funfedi_results/allure/test_allure.py
funfedi_results/archive/__init__.py
funfedi_results/archive/parse.py
funfedi_results/archive/test_parse.py
funfedi_results/archive/test_types.py
funfedi_results/archive/types.py
funfedi_results/codeberg/__init__.py
funfedi_results/codeberg/package_description.py
funfedi_results/codeberg/test_downloader.py
funfedi_results/codeberg/test_package_description.py
funfedi_results/codeberg/uploader.py
funfedi_results/transform/__init__.py
funfedi_results/transform/test_transform.py
funfedi_results-0.1.2.dist-info/METADATA
funfedi_results-0.1.2.dist-info/WHEEL
funfedi_results-0.1.2.dist-info/RECORD
