Metadata-Version: 2.4
Name: funfedi_results
Version: 0.1.2
Project-URL: repository, https://codeberg.org/funfedidev/funfedi_results
Requires-Python: >=3.11
Requires-Dist: click>=8.3.1
Requires-Dist: funfedi-connect>=0.1.3
Requires-Dist: semver>=3.0.4
